{"cameraMode":{"drawMode":0,"name":"Shaded","section":"Shading Mode"},"sceneLighting":false,"audioPlay":false,"sceneViewState":{"m_AlwaysRefresh":false,"showFog":true,"showSkybox":false,"showFlares":true,"showImageEffects":true,"showParticleSystems":true,"showVisualEffectGraphs":true,"m_FxEnabled":true},"in2DMode":false,"pivot":{"x":1.0,"y":0.0,"z":-1.0},"rotation":{"x":-0.39987650513648989,"y":0.5995194315910339,"z":-0.472543865442276,"w":-0.5073415637016296},"size":21.23676109313965,"orthographic":true}